[
  {
    "id": "spaghetti-bolognese",
    "imageUrl": "/images/recipes/spaghetti-bolognese.png",
    "defaultServings": 4,
    "ingredients": [
      {
        "id": "sb-1",
        "quantity": 400,
        "unit": "g",
        "category": "pantry"
      },
      {
        "id": "sb-2",
        "quantity": 500,
        "unit": "g",
        "category": "meat"
      },
      {
        "id": "sb-3",
        "quantity": 1,
        "unit": "piece",
        "category": "produce"
      },
      {
        "id": "sb-4",
        "quantity": 3,
        "unit": "piece",
        "category": "produce"
      },
      {
        "id": "sb-5",
        "quantity": 400,
        "unit": "g",
        "category": "pantry"
      },
      {
        "id": "sb-6",
        "quantity": 2,
        "unit": "tbsp",
        "category": "pantry"
      },
      {
        "id": "sb-7",
        "quantity": 2,
        "unit": "tbsp",
        "category": "pantry"
      },
      {
        "id": "sb-8",
        "quantity": 1,
        "unit": "tsp",
        "category": "spices"
      },
      {
        "id": "sb-9",
        "quantity": 0.5,
        "unit": "tsp",
        "category": "spices"
      },
      {
        "id": "sb-10",
        "quantity": 50,
        "unit": "g",
        "category": "dairy"
      }
    ]
  },
  {
    "id": "chicken-curry",
    "imageUrl": "/images/recipes/chicken-curry.png",
    "defaultServings": 4,
    "ingredients": [
      {
        "id": "cc-1",
        "quantity": 600,
        "unit": "g",
        "category": "meat"
      },
      {
        "id": "cc-2",
        "quantity": 2,
        "unit": "piece",
        "category": "produce"
      },
      {
        "id": "cc-3",
        "quantity": 4,
        "unit": "piece",
        "category": "produce"
      },
      {
        "id": "cc-4",
        "quantity": 1,
        "unit": "tbsp",
        "category": "produce"
      },
      {
        "id": "cc-5",
        "quantity": 400,
        "unit": "ml",
        "category": "pantry"
      },
      {
        "id": "cc-6",
        "quantity": 2,
        "unit": "tbsp",
        "category": "spices"
      },
      {
        "id": "cc-7",
        "quantity": 1,
        "unit": "tsp",
        "category": "spices"
      },
      {
        "id": "cc-8",
        "quantity": 0.5,
        "unit": "tsp",
        "category": "spices"
      },
      {
        "id": "cc-9",
        "quantity": 2,
        "unit": "tbsp",
        "category": "pantry"
      },
      {
        "id": "cc-10",
        "quantity": 1,
        "unit": "tsp",
        "category": "spices"
      },
      {
        "id": "cc-11",
        "quantity": 300,
        "unit": "g",
        "category": "pantry"
      }
    ]
  },
  {
    "id": "caesar-salad",
    "imageUrl": "/images/recipes/caesar-salad.png",
    "defaultServings": 2,
    "ingredients": [
      {
        "id": "cs-1",
        "quantity": 1,
        "unit": "piece",
        "category": "produce"
      },
      {
        "id": "cs-2",
        "quantity": 50,
        "unit": "g",
        "category": "dairy"
      },
      {
        "id": "cs-3",
        "quantity": 100,
        "unit": "g",
        "category": "pantry"
      },
      {
        "id": "cs-4",
        "quantity": 4,
        "unit": "tbsp",
        "category": "pantry"
      },
      {
        "id": "cs-5",
        "quantity": 2,
        "unit": "piece",
        "category": "produce"
      },
      {
        "id": "cs-6",
        "quantity": 2,
        "unit": "tbsp",
        "category": "produce"
      },
      {
        "id": "cs-7",
        "quantity": 3,
        "unit": "tbsp",
        "category": "dairy"
      },
      {
        "id": "cs-8",
        "quantity": 1,
        "unit": "tsp",
        "category": "pantry"
      },
      {
        "id": "cs-9",
        "quantity": 0.5,
        "unit": "tsp",
        "category": "spices"
      },
      {
        "id": "cs-10",
        "quantity": 0.25,
        "unit": "tsp",
        "category": "spices"
      }
    ]
  },
  {
    "id": "miso-honey-salmon",
    "imageUrl": "/images/recipes/miso-honey-salmon.png",
    "defaultServings": 2,
    "ingredients": [
      {
        "id": "mhs-1",
        "quantity": 400,
        "unit": "g",
        "category": "meat"
      },
      {
        "id": "mhs-2",
        "quantity": 2,
        "unit": "tbsp",
        "category": "pantry"
      },
      {
        "id": "mhs-3",
        "quantity": 2,
        "unit": "tbsp",
        "category": "pantry"
      },
      {
        "id": "mhs-4",
        "quantity": 1,
        "unit": "tbsp",
        "category": "pantry"
      },
      {
        "id": "mhs-5",
        "quantity": 1,
        "unit": "tbsp",
        "category": "pantry"
      },
      {
        "id": "mhs-6",
        "quantity": 2,
        "unit": "piece",
        "category": "produce"
      },
      {
        "id": "mhs-7",
        "quantity": 1,
        "unit": "tsp",
        "category": "produce"
      },
      {
        "id": "mhs-8",
        "quantity": 1,
        "unit": "tsp",
        "category": "pantry"
      },
      {
        "id": "mhs-9",
        "quantity": 2,
        "unit": "piece",
        "category": "produce"
      },
      {
        "id": "mhs-10",
        "quantity": 1,
        "unit": "tbsp",
        "category": "spices"
      },
      {
        "id": "mhs-11",
        "quantity": 200,
        "unit": "g",
        "category": "pantry"
      }
    ]
  },
  {
    "id": "korean-beef-bowls",
    "imageUrl": "/images/recipes/korean-beef-bowls.png",
    "defaultServings": 4,
    "ingredients": [
      {
        "id": "kbb-1",
        "quantity": 500,
        "unit": "g",
        "category": "meat"
      },
      {
        "id": "kbb-2",
        "quantity": 4,
        "unit": "tbsp",
        "category": "pantry"
      },
      {
        "id": "kbb-3",
        "quantity": 3,
        "unit": "tbsp",
        "category": "pantry"
      },
      {
        "id": "kbb-4",
        "quantity": 2,
        "unit": "tbsp",
        "category": "pantry"
      },
      {
        "id": "kbb-5",
        "quantity": 4,
        "unit": "piece",
        "category": "produce"
      },
      {
        "id": "kbb-6",
        "quantity": 1,
        "unit": "tbsp",
        "category": "produce"
      },
      {
        "id": "kbb-7",
        "quantity": 1,
        "unit": "tbsp",
        "category": "pantry"
      },
      {
        "id": "kbb-8",
        "quantity": 300,
        "unit": "g",
        "category": "pantry"
      },
      {
        "id": "kbb-9",
        "quantity": 3,
        "unit": "piece",
        "category": "produce"
      },
      {
        "id": "kbb-10",
        "quantity": 1,
        "unit": "piece",
        "category": "produce"
      },
      {
        "id": "kbb-11",
        "quantity": 1,
        "unit": "tbsp",
        "category": "spices"
      },
      {
        "id": "kbb-12",
        "quantity": 1,
        "unit": "tbsp",
        "category": "pantry"
      }
    ]
  },
  {
    "id": "coconut-shrimp",
    "imageUrl": "/images/recipes/coconut-shrimp.png",
    "defaultServings": 4,
    "ingredients": [
      {
        "id": "csh-1",
        "quantity": 500,
        "unit": "g",
        "category": "meat"
      },
      {
        "id": "csh-2",
        "quantity": 150,
        "unit": "g",
        "category": "pantry"
      },
      {
        "id": "csh-3",
        "quantity": 100,
        "unit": "g",
        "category": "pantry"
      },
      {
        "id": "csh-4",
        "quantity": 2,
        "unit": "piece",
        "category": "dairy"
      },
      {
        "id": "csh-5",
        "quantity": 1,
        "unit": "piece",
        "category": "produce"
      },
      {
        "id": "csh-6",
        "quantity": 0.5,
        "unit": "piece",
        "category": "produce"
      },
      {
        "id": "csh-7",
        "quantity": 1,
        "unit": "tbsp",
        "category": "produce"
      },
      {
        "id": "csh-8",
        "quantity": 1,
        "unit": "piece",
        "category": "produce"
      },
      {
        "id": "csh-9",
        "quantity": 1,
        "unit": "piece",
        "category": "produce"
      },
      {
        "id": "csh-10",
        "quantity": 250,
        "unit": "ml",
        "category": "pantry"
      },
      {
        "id": "csh-11",
        "quantity": 1,
        "unit": "tsp",
        "category": "spices"
      },
      {
        "id": "csh-12",
        "quantity": 0.5,
        "unit": "tsp",
        "category": "spices"
      }
    ]
  },
  {
    "id": "chicken-tikka-masala",
    "imageUrl": "/images/recipes/chicken-tikka-masala.png",
    "defaultServings": 4,
    "ingredients": [
      {
        "id": "ctm-1",
        "quantity": 600,
        "unit": "g",
        "category": "meat"
      },
      {
        "id": "ctm-2",
        "quantity": 150,
        "unit": "ml",
        "category": "dairy"
      },
      {
        "id": "ctm-3",
        "quantity": 200,
        "unit": "ml",
        "category": "dairy"
      },
      {
        "id": "ctm-4",
        "quantity": 400,
        "unit": "g",
        "category": "pantry"
      },
      {
        "id": "ctm-5",
        "quantity": 1,
        "unit": "piece",
        "category": "produce"
      },
      {
        "id": "ctm-6",
        "quantity": 4,
        "unit": "piece",
        "category": "produce"
      },
      {
        "id": "ctm-7",
        "quantity": 1,
        "unit": "tbsp",
        "category": "produce"
      },
      {
        "id": "ctm-8",
        "quantity": 2,
        "unit": "tsp",
        "category": "spices"
      },
      {
        "id": "ctm-9",
        "quantity": 1,
        "unit": "tsp",
        "category": "spices"
      },
      {
        "id": "ctm-10",
        "quantity": 1,
        "unit": "tsp",
        "category": "spices"
      },
      {
        "id": "ctm-11",
        "quantity": 30,
        "unit": "g",
        "category": "dairy"
      },
      {
        "id": "ctm-12",
        "quantity": 300,
        "unit": "g",
        "category": "pantry"
      }
    ]
  },
  {
    "id": "beef-fajita-bowls",
    "imageUrl": "/images/recipes/beef-fajita-bowls.png",
    "defaultServings": 4,
    "ingredients": [
      {
        "id": "bfb-1",
        "quantity": 500,
        "unit": "g",
        "category": "meat"
      },
      {
        "id": "bfb-2",
        "quantity": 2,
        "unit": "piece",
        "category": "produce"
      },
      {
        "id": "bfb-3",
        "quantity": 1,
        "unit": "piece",
        "category": "produce"
      },
      {
        "id": "bfb-4",
        "quantity": 2,
        "unit": "piece",
        "category": "produce"
      },
      {
        "id": "bfb-5",
        "quantity": 1,
        "unit": "tsp",
        "category": "spices"
      },
      {
        "id": "bfb-6",
        "quantity": 1,
        "unit": "tsp",
        "category": "spices"
      },
      {
        "id": "bfb-7",
        "quantity": 3,
        "unit": "piece",
        "category": "produce"
      },
      {
        "id": "bfb-8",
        "quantity": 300,
        "unit": "g",
        "category": "pantry"
      },
      {
        "id": "bfb-9",
        "quantity": 100,
        "unit": "ml",
        "category": "dairy"
      },
      {
        "id": "bfb-10",
        "quantity": 2,
        "unit": "tbsp",
        "category": "produce"
      },
      {
        "id": "bfb-11",
        "quantity": 2,
        "unit": "tbsp",
        "category": "pantry"
      }
    ]
  },
  {
    "id": "teriyaki-chicken",
    "imageUrl": "/images/recipes/teriyaki-chicken.png",
    "defaultServings": 4,
    "ingredients": [
      {
        "id": "tc-1",
        "quantity": 600,
        "unit": "g",
        "category": "meat"
      },
      {
        "id": "tc-2",
        "quantity": 4,
        "unit": "tbsp",
        "category": "pantry"
      },
      {
        "id": "tc-3",
        "quantity": 3,
        "unit": "tbsp",
        "category": "pantry"
      },
      {
        "id": "tc-4",
        "quantity": 2,
        "unit": "tbsp",
        "category": "pantry"
      },
      {
        "id": "tc-5",
        "quantity": 3,
        "unit": "piece",
        "category": "produce"
      },
      {
        "id": "tc-6",
        "quantity": 1,
        "unit": "tsp",
        "category": "produce"
      },
      {
        "id": "tc-7",
        "quantity": 300,
        "unit": "g",
        "category": "pantry"
      },
      {
        "id": "tc-8",
        "quantity": 300,
        "unit": "g",
        "category": "produce"
      },
      {
        "id": "tc-9",
        "quantity": 1,
        "unit": "tbsp",
        "category": "spices"
      },
      {
        "id": "tc-10",
        "quantity": 2,
        "unit": "piece",
        "category": "produce"
      }
    ]
  },
  {
    "id": "mushroom-risotto",
    "imageUrl": "/images/recipes/mushroom-risotto.png",
    "defaultServings": 4,
    "ingredients": [
      {
        "id": "mr-1",
        "quantity": 300,
        "unit": "g",
        "category": "pantry"
      },
      {
        "id": "mr-2",
        "quantity": 400,
        "unit": "g",
        "category": "produce"
      },
      {
        "id": "mr-3",
        "quantity": 1000,
        "unit": "ml",
        "category": "pantry"
      },
      {
        "id": "mr-4",
        "quantity": 150,
        "unit": "ml",
        "category": "pantry"
      },
      {
        "id": "mr-5",
        "quantity": 1,
        "unit": "piece",
        "category": "produce"
      },
      {
        "id": "mr-6",
        "quantity": 3,
        "unit": "piece",
        "category": "produce"
      },
      {
        "id": "mr-7",
        "quantity": 80,
        "unit": "g",
        "category": "dairy"
      },
      {
        "id": "mr-8",
        "quantity": 50,
        "unit": "g",
        "category": "dairy"
      },
      {
        "id": "mr-9",
        "quantity": 2,
        "unit": "tbsp",
        "category": "pantry"
      },
      {
        "id": "mr-10",
        "quantity": 1,
        "unit": "tsp",
        "category": "spices"
      }
    ]
  },
  {
    "id": "fish-tacos",
    "imageUrl": "/images/recipes/fish-tacos.png",
    "defaultServings": 4,
    "ingredients": [
      {
        "id": "ft-1",
        "quantity": 500,
        "unit": "g",
        "category": "meat"
      },
      {
        "id": "ft-2",
        "quantity": 150,
        "unit": "g",
        "category": "pantry"
      },
      {
        "id": "ft-3",
        "quantity": 200,
        "unit": "ml",
        "category": "pantry"
      },
      {
        "id": "ft-4",
        "quantity": 200,
        "unit": "g",
        "category": "produce"
      },
      {
        "id": "ft-5",
        "quantity": 4,
        "unit": "tbsp",
        "category": "dairy"
      },
      {
        "id": "ft-6",
        "quantity": 2,
        "unit": "piece",
        "category": "produce"
      },
      {
        "id": "ft-7",
        "quantity": 8,
        "unit": "piece",
        "category": "pantry"
      },
      {
        "id": "ft-8",
        "quantity": 1,
        "unit": "tbsp",
        "category": "spices"
      },
      {
        "id": "ft-9",
        "quantity": 300,
        "unit": "ml",
        "category": "pantry"
      },
      {
        "id": "ft-10",
        "quantity": 2,
        "unit": "tbsp",
        "category": "produce"
      }
    ]
  },
  {
    "id": "pork-stir-fry",
    "imageUrl": "/images/recipes/pork-stir-fry.png",
    "defaultServings": 4,
    "ingredients": [
      {
        "id": "psf-1",
        "quantity": 500,
        "unit": "g",
        "category": "meat"
      },
      {
        "id": "psf-2",
        "quantity": 2,
        "unit": "piece",
        "category": "produce"
      },
      {
        "id": "psf-3",
        "quantity": 200,
        "unit": "g",
        "category": "produce"
      },
      {
        "id": "psf-4",
        "quantity": 3,
        "unit": "tbsp",
        "category": "pantry"
      },
      {
        "id": "psf-5",
        "quantity": 2,
        "unit": "tbsp",
        "category": "pantry"
      },
      {
        "id": "psf-6",
        "quantity": 1,
        "unit": "tbsp",
        "category": "pantry"
      },
      {
        "id": "psf-7",
        "quantity": 4,
        "unit": "piece",
        "category": "produce"
      },
      {
        "id": "psf-8",
        "quantity": 300,
        "unit": "g",
        "category": "pantry"
      },
      {
        "id": "psf-9",
        "quantity": 2,
        "unit": "tbsp",
        "category": "pantry"
      },
      {
        "id": "psf-10",
        "quantity": 1,
        "unit": "tbsp",
        "category": "pantry"
      }
    ]
  },
  {
    "id": "greek-chicken-bowls",
    "imageUrl": "/images/recipes/greek-chicken-bowls.png",
    "defaultServings": 4,
    "ingredients": [
      {
        "id": "gcb-1",
        "quantity": 600,
        "unit": "g",
        "category": "meat"
      },
      {
        "id": "gcb-2",
        "quantity": 1,
        "unit": "piece",
        "category": "produce"
      },
      {
        "id": "gcb-3",
        "quantity": 200,
        "unit": "g",
        "category": "produce"
      },
      {
        "id": "gcb-4",
        "quantity": 0.5,
        "unit": "piece",
        "category": "produce"
      },
      {
        "id": "gcb-5",
        "quantity": 100,
        "unit": "g",
        "category": "dairy"
      },
      {
        "id": "gcb-6",
        "quantity": 150,
        "unit": "ml",
        "category": "dairy"
      },
      {
        "id": "gcb-7",
        "quantity": 1,
        "unit": "piece",
        "category": "produce"
      },
      {
        "id": "gcb-8",
        "quantity": 1,
        "unit": "tsp",
        "category": "spices"
      },
      {
        "id": "gcb-9",
        "quantity": 300,
        "unit": "g",
        "category": "pantry"
      },
      {
        "id": "gcb-10",
        "quantity": 3,
        "unit": "tbsp",
        "category": "pantry"
      },
      {
        "id": "gcb-11",
        "quantity": 2,
        "unit": "piece",
        "category": "produce"
      }
    ]
  },
  {
    "id": "shrimp-scampi",
    "imageUrl": "/images/recipes/shrimp-scampi.png",
    "defaultServings": 4,
    "ingredients": [
      {
        "id": "ss-1",
        "quantity": 500,
        "unit": "g",
        "category": "meat"
      },
      {
        "id": "ss-2",
        "quantity": 400,
        "unit": "g",
        "category": "pantry"
      },
      {
        "id": "ss-3",
        "quantity": 60,
        "unit": "g",
        "category": "dairy"
      },
      {
        "id": "ss-4",
        "quantity": 6,
        "unit": "piece",
        "category": "produce"
      },
      {
        "id": "ss-5",
        "quantity": 150,
        "unit": "ml",
        "category": "pantry"
      },
      {
        "id": "ss-6",
        "quantity": 1,
        "unit": "piece",
        "category": "produce"
      },
      {
        "id": "ss-7",
        "quantity": 0.5,
        "unit": "tsp",
        "category": "spices"
      },
      {
        "id": "ss-8",
        "quantity": 3,
        "unit": "tbsp",
        "category": "produce"
      },
      {
        "id": "ss-9",
        "quantity": 2,
        "unit": "tbsp",
        "category": "pantry"
      }
    ]
  },
  {
    "id": "bbq-chicken",
    "imageUrl": "/images/recipes/bbq-chicken.png",
    "defaultServings": 4,
    "ingredients": [
      {
        "id": "bbq-1",
        "quantity": 800,
        "unit": "g",
        "category": "meat"
      },
      {
        "id": "bbq-2",
        "quantity": 100,
        "unit": "ml",
        "category": "pantry"
      },
      {
        "id": "bbq-3",
        "quantity": 3,
        "unit": "tbsp",
        "category": "pantry"
      },
      {
        "id": "bbq-4",
        "quantity": 2,
        "unit": "tbsp",
        "category": "pantry"
      },
      {
        "id": "bbq-5",
        "quantity": 1,
        "unit": "tbsp",
        "category": "pantry"
      },
      {
        "id": "bbq-6",
        "quantity": 1,
        "unit": "tsp",
        "category": "spices"
      },
      {
        "id": "bbq-7",
        "quantity": 0.5,
        "unit": "tsp",
        "category": "spices"
      },
      {
        "id": "bbq-8",
        "quantity": 4,
        "unit": "piece",
        "category": "produce"
      },
      {
        "id": "bbq-9",
        "quantity": 300,
        "unit": "g",
        "category": "produce"
      },
      {
        "id": "bbq-10",
        "quantity": 4,
        "unit": "tbsp",
        "category": "dairy"
      }
    ]
  },
  {
    "id": "vegetable-pad-thai",
    "imageUrl": "/images/recipes/vegetable-pad-thai.png",
    "defaultServings": 4,
    "ingredients": [
      {
        "id": "vpt-1",
        "quantity": 300,
        "unit": "g",
        "category": "pantry"
      },
      {
        "id": "vpt-2",
        "quantity": 300,
        "unit": "g",
        "category": "produce"
      },
      {
        "id": "vpt-3",
        "quantity": 200,
        "unit": "g",
        "category": "produce"
      },
      {
        "id": "vpt-4",
        "quantity": 2,
        "unit": "piece",
        "category": "dairy"
      },
      {
        "id": "vpt-5",
        "quantity": 2,
        "unit": "tbsp",
        "category": "pantry"
      },
      {
        "id": "vpt-6",
        "quantity": 2,
        "unit": "tbsp",
        "category": "pantry"
      },
      {
        "id": "vpt-7",
        "quantity": 2,
        "unit": "tbsp",
        "category": "pantry"
      },
      {
        "id": "vpt-8",
        "quantity": 50,
        "unit": "g",
        "category": "pantry"
      },
      {
        "id": "vpt-9",
        "quantity": 3,
        "unit": "piece",
        "category": "produce"
      },
      {
        "id": "vpt-10",
        "quantity": 1,
        "unit": "piece",
        "category": "produce"
      },
      {
        "id": "vpt-11",
        "quantity": 3,
        "unit": "tbsp",
        "category": "pantry"
      }
    ]
  },
  {
    "id": "lamb-kofta",
    "imageUrl": "/images/recipes/lamb-kofta.png",
    "defaultServings": 4,
    "ingredients": [
      {
        "id": "lk-1",
        "quantity": 500,
        "unit": "g",
        "category": "meat"
      },
      {
        "id": "lk-2",
        "quantity": 1,
        "unit": "piece",
        "category": "produce"
      },
      {
        "id": "lk-3",
        "quantity": 3,
        "unit": "piece",
        "category": "produce"
      },
      {
        "id": "lk-4",
        "quantity": 1,
        "unit": "tsp",
        "category": "spices"
      },
      {
        "id": "lk-5",
        "quantity": 1,
        "unit": "tsp",
        "category": "spices"
      },
      {
        "id": "lk-6",
        "quantity": 200,
        "unit": "ml",
        "category": "dairy"
      },
      {
        "id": "lk-7",
        "quantity": 3,
        "unit": "tbsp",
        "category": "produce"
      },
      {
        "id": "lk-8",
        "quantity": 4,
        "unit": "piece",
        "category": "pantry"
      },
      {
        "id": "lk-9",
        "quantity": 1,
        "unit": "piece",
        "category": "produce"
      },
      {
        "id": "lk-10",
        "quantity": 200,
        "unit": "g",
        "category": "produce"
      }
    ]
  },
  {
    "id": "cajun-shrimp-pasta",
    "imageUrl": "/images/recipes/cajun-shrimp-pasta.png",
    "defaultServings": 4,
    "ingredients": [
      {
        "id": "csp-1",
        "quantity": 400,
        "unit": "g",
        "category": "meat"
      },
      {
        "id": "csp-2",
        "quantity": 400,
        "unit": "g",
        "category": "pantry"
      },
      {
        "id": "csp-3",
        "quantity": 250,
        "unit": "ml",
        "category": "dairy"
      },
      {
        "id": "csp-4",
        "quantity": 50,
        "unit": "g",
        "category": "dairy"
      },
      {
        "id": "csp-5",
        "quantity": 2,
        "unit": "tbsp",
        "category": "spices"
      },
      {
        "id": "csp-6",
        "quantity": 4,
        "unit": "piece",
        "category": "produce"
      },
      {
        "id": "csp-7",
        "quantity": 1,
        "unit": "piece",
        "category": "produce"
      },
      {
        "id": "csp-8",
        "quantity": 30,
        "unit": "g",
        "category": "dairy"
      },
      {
        "id": "csp-9",
        "quantity": 2,
        "unit": "tbsp",
        "category": "produce"
      }
    ]
  },
  {
    "id": "honey-garlic-pork",
    "imageUrl": "/images/recipes/honey-garlic-pork.png",
    "defaultServings": 4,
    "ingredients": [
      {
        "id": "hgp-1",
        "quantity": 4,
        "unit": "piece",
        "category": "meat"
      },
      {
        "id": "hgp-2",
        "quantity": 4,
        "unit": "tbsp",
        "category": "pantry"
      },
      {
        "id": "hgp-3",
        "quantity": 3,
        "unit": "tbsp",
        "category": "pantry"
      },
      {
        "id": "hgp-4",
        "quantity": 6,
        "unit": "piece",
        "category": "produce"
      },
      {
        "id": "hgp-5",
        "quantity": 30,
        "unit": "g",
        "category": "dairy"
      },
      {
        "id": "hgp-6",
        "quantity": 600,
        "unit": "g",
        "category": "pantry"
      },
      {
        "id": "hgp-7",
        "quantity": 300,
        "unit": "g",
        "category": "produce"
      },
      {
        "id": "hgp-8",
        "quantity": 2,
        "unit": "tbsp",
        "category": "pantry"
      },
      {
        "id": "hgp-9",
        "quantity": 1,
        "unit": "tsp",
        "category": "spices"
      }
    ]
  },
  {
    "id": "tuscan-chicken",
    "imageUrl": "/images/recipes/tuscan-chicken.png",
    "defaultServings": 4,
    "ingredients": [
      {
        "id": "tuc-1",
        "quantity": 600,
        "unit": "g",
        "category": "meat"
      },
      {
        "id": "tuc-2",
        "quantity": 100,
        "unit": "g",
        "category": "pantry"
      },
      {
        "id": "tuc-3",
        "quantity": 150,
        "unit": "g",
        "category": "produce"
      },
      {
        "id": "tuc-4",
        "quantity": 200,
        "unit": "ml",
        "category": "dairy"
      },
      {
        "id": "tuc-5",
        "quantity": 50,
        "unit": "g",
        "category": "dairy"
      },
      {
        "id": "tuc-6",
        "quantity": 4,
        "unit": "piece",
        "category": "produce"
      },
      {
        "id": "tuc-7",
        "quantity": 1,
        "unit": "tsp",
        "category": "spices"
      },
      {
        "id": "tuc-8",
        "quantity": 2,
        "unit": "tbsp",
        "category": "pantry"
      },
      {
        "id": "tuc-9",
        "quantity": 300,
        "unit": "g",
        "category": "pantry"
      }
    ]
  },
  {
    "id": "beef-bulgogi",
    "imageUrl": "/images/recipes/beef-bulgogi.png",
    "defaultServings": 4,
    "ingredients": [
      {
        "id": "bb-1",
        "quantity": 500,
        "unit": "g",
        "category": "meat"
      },
      {
        "id": "bb-2",
        "quantity": 0.5,
        "unit": "piece",
        "category": "produce"
      },
      {
        "id": "bb-3",
        "quantity": 4,
        "unit": "tbsp",
        "category": "pantry"
      },
      {
        "id": "bb-4",
        "quantity": 2,
        "unit": "tbsp",
        "category": "pantry"
      },
      {
        "id": "bb-5",
        "quantity": 2,
        "unit": "tbsp",
        "category": "pantry"
      },
      {
        "id": "bb-6",
        "quantity": 5,
        "unit": "piece",
        "category": "produce"
      },
      {
        "id": "bb-7",
        "quantity": 1,
        "unit": "tbsp",
        "category": "produce"
      },
      {
        "id": "bb-8",
        "quantity": 4,
        "unit": "piece",
        "category": "produce"
      },
      {
        "id": "bb-9",
        "quantity": 300,
        "unit": "g",
        "category": "pantry"
      },
      {
        "id": "bb-10",
        "quantity": 1,
        "unit": "tbsp",
        "category": "spices"
      }
    ]
  },
  {
    "id": "lemon-herb-chicken",
    "imageUrl": "/images/recipes/lemon-herb-chicken.png",
    "defaultServings": 4,
    "ingredients": [
      {
        "id": "lhc-1",
        "quantity": 800,
        "unit": "g",
        "category": "meat"
      },
      {
        "id": "lhc-2",
        "quantity": 2,
        "unit": "piece",
        "category": "produce"
      },
      {
        "id": "lhc-3",
        "quantity": 2,
        "unit": "tbsp",
        "category": "produce"
      },
      {
        "id": "lhc-4",
        "quantity": 1,
        "unit": "tbsp",
        "category": "produce"
      },
      {
        "id": "lhc-5",
        "quantity": 6,
        "unit": "piece",
        "category": "produce"
      },
      {
        "id": "lhc-6",
        "quantity": 4,
        "unit": "tbsp",
        "category": "pantry"
      },
      {
        "id": "lhc-7",
        "quantity": 500,
        "unit": "g",
        "category": "produce"
      },
      {
        "id": "lhc-8",
        "quantity": 300,
        "unit": "g",
        "category": "produce"
      }
    ]
  },
  {
    "id": "thai-basil-chicken",
    "imageUrl": "/images/recipes/thai-basil-chicken.png",
    "defaultServings": 4,
    "ingredients": [
      {
        "id": "tbc-1",
        "quantity": 500,
        "unit": "g",
        "category": "meat"
      },
      {
        "id": "tbc-2",
        "quantity": 1,
        "unit": "cup",
        "category": "produce"
      },
      {
        "id": "tbc-3",
        "quantity": 3,
        "unit": "piece",
        "category": "produce"
      },
      {
        "id": "tbc-4",
        "quantity": 6,
        "unit": "piece",
        "category": "produce"
      },
      {
        "id": "tbc-5",
        "quantity": 2,
        "unit": "tbsp",
        "category": "pantry"
      },
      {
        "id": "tbc-6",
        "quantity": 2,
        "unit": "tbsp",
        "category": "pantry"
      },
      {
        "id": "tbc-7",
        "quantity": 1,
        "unit": "tbsp",
        "category": "pantry"
      },
      {
        "id": "tbc-8",
        "quantity": 1,
        "unit": "tsp",
        "category": "pantry"
      },
      {
        "id": "tbc-9",
        "quantity": 300,
        "unit": "g",
        "category": "pantry"
      },
      {
        "id": "tbc-10",
        "quantity": 2,
        "unit": "tbsp",
        "category": "pantry"
      }
    ]
  },
  {
    "id": "salmon-teriyaki-bowl",
    "imageUrl": "/images/recipes/salmon-teriyaki-bowl.png",
    "defaultServings": 2,
    "ingredients": [
      {
        "id": "stb-1",
        "quantity": 400,
        "unit": "g",
        "category": "meat"
      },
      {
        "id": "stb-2",
        "quantity": 3,
        "unit": "tbsp",
        "category": "pantry"
      },
      {
        "id": "stb-3",
        "quantity": 2,
        "unit": "tbsp",
        "category": "pantry"
      },
      {
        "id": "stb-4",
        "quantity": 1,
        "unit": "tbsp",
        "category": "pantry"
      },
      {
        "id": "stb-5",
        "quantity": 200,
        "unit": "g",
        "category": "pantry"
      },
      {
        "id": "stb-6",
        "quantity": 100,
        "unit": "g",
        "category": "produce"
      },
      {
        "id": "stb-7",
        "quantity": 30,
        "unit": "g",
        "category": "pantry"
      },
      {
        "id": "stb-8",
        "quantity": 1,
        "unit": "piece",
        "category": "produce"
      },
      {
        "id": "stb-9",
        "quantity": 1,
        "unit": "tbsp",
        "category": "spices"
      },
      {
        "id": "stb-10",
        "quantity": 1,
        "unit": "piece",
        "category": "pantry"
      }
    ]
  },
  {
    "id": "moroccan-chicken",
    "imageUrl": "/images/recipes/moroccan-chicken.png",
    "defaultServings": 4,
    "ingredients": [
      {
        "id": "mc-1",
        "quantity": 800,
        "unit": "g",
        "category": "meat"
      },
      {
        "id": "mc-2",
        "quantity": 2,
        "unit": "piece",
        "category": "pantry"
      },
      {
        "id": "mc-3",
        "quantity": 100,
        "unit": "g",
        "category": "pantry"
      },
      {
        "id": "mc-4",
        "quantity": 1,
        "unit": "piece",
        "category": "produce"
      },
      {
        "id": "mc-5",
        "quantity": 4,
        "unit": "piece",
        "category": "produce"
      },
      {
        "id": "mc-6",
        "quantity": 1,
        "unit": "tsp",
        "category": "spices"
      },
      {
        "id": "mc-7",
        "quantity": 0.5,
        "unit": "tsp",
        "category": "spices"
      },
      {
        "id": "mc-8",
        "quantity": 1,
        "unit": "pinch",
        "category": "spices"
      },
      {
        "id": "mc-9",
        "quantity": 300,
        "unit": "g",
        "category": "pantry"
      },
      {
        "id": "mc-10",
        "quantity": 3,
        "unit": "tbsp",
        "category": "produce"
      },
      {
        "id": "mc-11",
        "quantity": 300,
        "unit": "ml",
        "category": "pantry"
      }
    ]
  },
  {
    "id": "black-bean-tacos",
    "imageUrl": "/images/recipes/black-bean-tacos.png",
    "defaultServings": 4,
    "ingredients": [
      {
        "id": "bbt-1",
        "quantity": 400,
        "unit": "g",
        "category": "pantry"
      },
      {
        "id": "bbt-2",
        "quantity": 8,
        "unit": "piece",
        "category": "pantry"
      },
      {
        "id": "bbt-3",
        "quantity": 2,
        "unit": "piece",
        "category": "produce"
      },
      {
        "id": "bbt-4",
        "quantity": 0.5,
        "unit": "piece",
        "category": "produce"
      },
      {
        "id": "bbt-5",
        "quantity": 2,
        "unit": "piece",
        "category": "produce"
      },
      {
        "id": "bbt-6",
        "quantity": 1,
        "unit": "tsp",
        "category": "spices"
      },
      {
        "id": "bbt-7",
        "quantity": 1,
        "unit": "tbsp",
        "category": "spices"
      },
      {
        "id": "bbt-8",
        "quantity": 3,
        "unit": "tbsp",
        "category": "produce"
      },
      {
        "id": "bbt-9",
        "quantity": 100,
        "unit": "g",
        "category": "dairy"
      },
      {
        "id": "bbt-10",
        "quantity": 100,
        "unit": "ml",
        "category": "pantry"
      }
    ]
  },
  {
    "id": "ginger-beef",
    "imageUrl": "/images/recipes/ginger-beef.png",
    "defaultServings": 4,
    "ingredients": [
      {
        "id": "gb-1",
        "quantity": 500,
        "unit": "g",
        "category": "meat"
      },
      {
        "id": "gb-2",
        "quantity": 3,
        "unit": "tbsp",
        "category": "produce"
      },
      {
        "id": "gb-3",
        "quantity": 4,
        "unit": "piece",
        "category": "produce"
      },
      {
        "id": "gb-4",
        "quantity": 3,
        "unit": "tbsp",
        "category": "pantry"
      },
      {
        "id": "gb-5",
        "quantity": 2,
        "unit": "tbsp",
        "category": "pantry"
      },
      {
        "id": "gb-6",
        "quantity": 2,
        "unit": "tbsp",
        "category": "pantry"
      },
      {
        "id": "gb-7",
        "quantity": 2,
        "unit": "piece",
        "category": "produce"
      },
      {
        "id": "gb-8",
        "quantity": 2,
        "unit": "tbsp",
        "category": "pantry"
      },
      {
        "id": "gb-9",
        "quantity": 300,
        "unit": "g",
        "category": "pantry"
      },
      {
        "id": "gb-10",
        "quantity": 3,
        "unit": "tbsp",
        "category": "pantry"
      }
    ]
  },
  {
    "id": "chicken-parmesan",
    "imageUrl": "/images/recipes/chicken-parmesan.png",
    "defaultServings": 4,
    "ingredients": [
      {
        "id": "cp-1",
        "quantity": 600,
        "unit": "g",
        "category": "meat"
      },
      {
        "id": "cp-2",
        "quantity": 150,
        "unit": "g",
        "category": "pantry"
      },
      {
        "id": "cp-3",
        "quantity": 80,
        "unit": "g",
        "category": "dairy"
      },
      {
        "id": "cp-4",
        "quantity": 150,
        "unit": "g",
        "category": "dairy"
      },
      {
        "id": "cp-5",
        "quantity": 400,
        "unit": "ml",
        "category": "pantry"
      },
      {
        "id": "cp-6",
        "quantity": 2,
        "unit": "piece",
        "category": "dairy"
      },
      {
        "id": "cp-7",
        "quantity": 100,
        "unit": "g",
        "category": "pantry"
      },
      {
        "id": "cp-8",
        "quantity": 400,
        "unit": "g",
        "category": "pantry"
      },
      {
        "id": "cp-9",
        "quantity": 2,
        "unit": "tbsp",
        "category": "produce"
      },
      {
        "id": "cp-10",
        "quantity": 4,
        "unit": "tbsp",
        "category": "pantry"
      }
    ]
  },
  {
    "id": "coconut-curry-soup",
    "imageUrl": "/images/recipes/coconut-curry-soup.png",
    "defaultServings": 4,
    "ingredients": [
      {
        "id": "ccs-1",
        "quantity": 400,
        "unit": "ml",
        "category": "pantry"
      },
      {
        "id": "ccs-2",
        "quantity": 500,
        "unit": "ml",
        "category": "pantry"
      },
      {
        "id": "ccs-3",
        "quantity": 2,
        "unit": "tbsp",
        "category": "pantry"
      },
      {
        "id": "ccs-4",
        "quantity": 200,
        "unit": "g",
        "category": "pantry"
      },
      {
        "id": "ccs-5",
        "quantity": 300,
        "unit": "g",
        "category": "produce"
      },
      {
        "id": "ccs-6",
        "quantity": 200,
        "unit": "g",
        "category": "produce"
      },
      {
        "id": "ccs-7",
        "quantity": 200,
        "unit": "g",
        "category": "produce"
      },
      {
        "id": "ccs-8",
        "quantity": 1,
        "unit": "piece",
        "category": "produce"
      },
      {
        "id": "ccs-9",
        "quantity": 3,
        "unit": "tbsp",
        "category": "produce"
      },
      {
        "id": "ccs-10",
        "quantity": 1,
        "unit": "tbsp",
        "category": "pantry"
      }
    ]
  },
  {
    "id": "mediterranean-bowl",
    "imageUrl": "/images/recipes/mediterranean-bowl.png",
    "defaultServings": 4,
    "ingredients": [
      {
        "id": "mgb-1",
        "quantity": 200,
        "unit": "g",
        "category": "pantry"
      },
      {
        "id": "mgb-2",
        "quantity": 12,
        "unit": "piece",
        "category": "pantry"
      },
      {
        "id": "mgb-3",
        "quantity": 200,
        "unit": "g",
        "category": "dairy"
      },
      {
        "id": "mgb-4",
        "quantity": 1,
        "unit": "piece",
        "category": "produce"
      },
      {
        "id": "mgb-5",
        "quantity": 200,
        "unit": "g",
        "category": "produce"
      },
      {
        "id": "mgb-6",
        "quantity": 0.5,
        "unit": "piece",
        "category": "produce"
      },
      {
        "id": "mgb-7",
        "quantity": 100,
        "unit": "g",
        "category": "dairy"
      },
      {
        "id": "mgb-8",
        "quantity": 50,
        "unit": "g",
        "category": "pantry"
      },
      {
        "id": "mgb-9",
        "quantity": 1,
        "unit": "piece",
        "category": "produce"
      },
      {
        "id": "mgb-10",
        "quantity": 3,
        "unit": "tbsp",
        "category": "pantry"
      }
    ]
  },
  {
    "id": "sesame-crusted-tuna",
    "imageUrl": "/images/recipes/sesame-crusted-tuna.png",
    "defaultServings": 2,
    "ingredients": [
      {
        "id": "sct-1",
        "quantity": 400,
        "unit": "g",
        "category": "meat"
      },
      {
        "id": "sct-2",
        "quantity": 4,
        "unit": "tbsp",
        "category": "spices"
      },
      {
        "id": "sct-3",
        "quantity": 2,
        "unit": "tbsp",
        "category": "pantry"
      },
      {
        "id": "sct-4",
        "quantity": 1,
        "unit": "tsp",
        "category": "pantry"
      },
      {
        "id": "sct-5",
        "quantity": 3,
        "unit": "tbsp",
        "category": "dairy"
      },
      {
        "id": "sct-6",
        "quantity": 150,
        "unit": "g",
        "category": "produce"
      },
      {
        "id": "sct-7",
        "quantity": 2,
        "unit": "tbsp",
        "category": "pantry"
      },
      {
        "id": "sct-8",
        "quantity": 1,
        "unit": "tbsp",
        "category": "pantry"
      },
      {
        "id": "sct-9",
        "quantity": 1,
        "unit": "tsp",
        "category": "produce"
      }
    ]
  },
  {
    "id": "butter-chicken",
    "imageUrl": "/images/recipes/butter-chicken.png",
    "defaultServings": 4,
    "ingredients": [
      {
        "id": "bc-1",
        "quantity": 600,
        "unit": "g",
        "category": "meat"
      },
      {
        "id": "bc-2",
        "quantity": 60,
        "unit": "g",
        "category": "dairy"
      },
      {
        "id": "bc-3",
        "quantity": 200,
        "unit": "ml",
        "category": "dairy"
      },
      {
        "id": "bc-4",
        "quantity": 300,
        "unit": "ml",
        "category": "pantry"
      },
      {
        "id": "bc-5",
        "quantity": 1,
        "unit": "piece",
        "category": "produce"
      },
      {
        "id": "bc-6",
        "quantity": 4,
        "unit": "piece",
        "category": "produce"
      },
      {
        "id": "bc-7",
        "quantity": 2,
        "unit": "tsp",
        "category": "spices"
      },
      {
        "id": "bc-8",
        "quantity": 1,
        "unit": "tsp",
        "category": "spices"
      },
      {
        "id": "bc-9",
        "quantity": 300,
        "unit": "g",
        "category": "pantry"
      },
      {
        "id": "bc-10",
        "quantity": 4,
        "unit": "piece",
        "category": "pantry"
      },
      {
        "id": "bc-11",
        "quantity": 2,
        "unit": "tbsp",
        "category": "produce"
      }
    ]
  },
  {
    "id": "pesto-pasta",
    "imageUrl": "/images/recipes/pesto-pasta.png",
    "defaultServings": 4,
    "ingredients": [
      {
        "id": "pp-1",
        "quantity": 400,
        "unit": "g",
        "category": "pantry"
      },
      {
        "id": "pp-2",
        "quantity": 50,
        "unit": "g",
        "category": "produce"
      },
      {
        "id": "pp-3",
        "quantity": 50,
        "unit": "g",
        "category": "pantry"
      },
      {
        "id": "pp-4",
        "quantity": 80,
        "unit": "g",
        "category": "dairy"
      },
      {
        "id": "pp-5",
        "quantity": 3,
        "unit": "piece",
        "category": "produce"
      },
      {
        "id": "pp-6",
        "quantity": 100,
        "unit": "ml",
        "category": "pantry"
      },
      {
        "id": "pp-7",
        "quantity": 200,
        "unit": "g",
        "category": "produce"
      },
      {
        "id": "pp-8",
        "quantity": 100,
        "unit": "ml",
        "category": "dairy"
      },
      {
        "id": "pp-9",
        "quantity": 0.5,
        "unit": "piece",
        "category": "produce"
      }
    ]
  },
  {
    "id": "chicken-shawarma",
    "imageUrl": "/images/recipes/chicken-shawarma.png",
    "defaultServings": 4,
    "ingredients": [
      {
        "id": "csw-1",
        "quantity": 600,
        "unit": "g",
        "category": "meat"
      },
      {
        "id": "csw-2",
        "quantity": 1,
        "unit": "tsp",
        "category": "spices"
      },
      {
        "id": "csw-3",
        "quantity": 1,
        "unit": "tsp",
        "category": "spices"
      },
      {
        "id": "csw-4",
        "quantity": 1,
        "unit": "tsp",
        "category": "spices"
      },
      {
        "id": "csw-5",
        "quantity": 0.5,
        "unit": "tsp",
        "category": "spices"
      },
      {
        "id": "csw-6",
        "quantity": 150,
        "unit": "ml",
        "category": "dairy"
      },
      {
        "id": "csw-7",
        "quantity": 6,
        "unit": "piece",
        "category": "produce"
      },
      {
        "id": "csw-8",
        "quantity": 4,
        "unit": "piece",
        "category": "pantry"
      },
      {
        "id": "csw-9",
        "quantity": 100,
        "unit": "g",
        "category": "pantry"
      },
      {
        "id": "csw-10",
        "quantity": 2,
        "unit": "piece",
        "category": "produce"
      },
      {
        "id": "csw-11",
        "quantity": 100,
        "unit": "g",
        "category": "produce"
      }
    ]
  },
  {
    "id": "shrimp-fried-rice",
    "imageUrl": "/images/recipes/shrimp-fried-rice.png",
    "defaultServings": 4,
    "ingredients": [
      {
        "id": "sfr-1",
        "quantity": 300,
        "unit": "g",
        "category": "meat"
      },
      {
        "id": "sfr-2",
        "quantity": 500,
        "unit": "g",
        "category": "pantry"
      },
      {
        "id": "sfr-3",
        "quantity": 3,
        "unit": "piece",
        "category": "dairy"
      },
      {
        "id": "sfr-4",
        "quantity": 100,
        "unit": "g",
        "category": "produce"
      },
      {
        "id": "sfr-5",
        "quantity": 1,
        "unit": "piece",
        "category": "produce"
      },
      {
        "id": "sfr-6",
        "quantity": 4,
        "unit": "piece",
        "category": "produce"
      },
      {
        "id": "sfr-7",
        "quantity": 3,
        "unit": "tbsp",
        "category": "pantry"
      },
      {
        "id": "sfr-8",
        "quantity": 1,
        "unit": "tbsp",
        "category": "pantry"
      },
      {
        "id": "sfr-9",
        "quantity": 3,
        "unit": "piece",
        "category": "produce"
      },
      {
        "id": "sfr-10",
        "quantity": 3,
        "unit": "tbsp",
        "category": "pantry"
      }
    ]
  },
  {
    "id": "stuffed-peppers",
    "imageUrl": "/images/recipes/stuffed-peppers.png",
    "defaultServings": 4,
    "ingredients": [
      {
        "id": "sp-1",
        "quantity": 4,
        "unit": "piece",
        "category": "produce"
      },
      {
        "id": "sp-2",
        "quantity": 400,
        "unit": "g",
        "category": "meat"
      },
      {
        "id": "sp-3",
        "quantity": 150,
        "unit": "g",
        "category": "pantry"
      },
      {
        "id": "sp-4",
        "quantity": 400,
        "unit": "g",
        "category": "pantry"
      },
      {
        "id": "sp-5",
        "quantity": 1,
        "unit": "piece",
        "category": "produce"
      },
      {
        "id": "sp-6",
        "quantity": 3,
        "unit": "piece",
        "category": "produce"
      },
      {
        "id": "sp-7",
        "quantity": 1,
        "unit": "tsp",
        "category": "spices"
      },
      {
        "id": "sp-8",
        "quantity": 150,
        "unit": "g",
        "category": "dairy"
      },
      {
        "id": "sp-9",
        "quantity": 2,
        "unit": "tbsp",
        "category": "produce"
      }
    ]
  },
  {
    "id": "orange-chicken",
    "imageUrl": "/images/recipes/orange-chicken.png",
    "defaultServings": 4,
    "ingredients": [
      {
        "id": "oc-1",
        "quantity": 600,
        "unit": "g",
        "category": "meat"
      },
      {
        "id": "oc-2",
        "quantity": 150,
        "unit": "ml",
        "category": "produce"
      },
      {
        "id": "oc-3",
        "quantity": 3,
        "unit": "tbsp",
        "category": "pantry"
      },
      {
        "id": "oc-4",
        "quantity": 3,
        "unit": "tbsp",
        "category": "pantry"
      },
      {
        "id": "oc-5",
        "quantity": 2,
        "unit": "tbsp",
        "category": "pantry"
      },
      {
        "id": "oc-6",
        "quantity": 1,
        "unit": "tbsp",
        "category": "produce"
      },
      {
        "id": "oc-7",
        "quantity": 100,
        "unit": "g",
        "category": "pantry"
      },
      {
        "id": "oc-8",
        "quantity": 3,
        "unit": "piece",
        "category": "produce"
      },
      {
        "id": "oc-9",
        "quantity": 300,
        "unit": "g",
        "category": "pantry"
      },
      {
        "id": "oc-10",
        "quantity": 300,
        "unit": "ml",
        "category": "pantry"
      },
      {
        "id": "oc-11",
        "quantity": 2,
        "unit": "piece",
        "category": "produce"
      }
    ]
  },
  {
    "id": "lamb-chops",
    "imageUrl": "/images/recipes/lamb-chops.png",
    "defaultServings": 2,
    "ingredients": [
      {
        "id": "lc-1",
        "quantity": 6,
        "unit": "piece",
        "category": "meat"
      },
      {
        "id": "lc-2",
        "quantity": 2,
        "unit": "tbsp",
        "category": "produce"
      },
      {
        "id": "lc-3",
        "quantity": 4,
        "unit": "piece",
        "category": "produce"
      },
      {
        "id": "lc-4",
        "quantity": 2,
        "unit": "tbsp",
        "category": "pantry"
      },
      {
        "id": "lc-5",
        "quantity": 50,
        "unit": "g",
        "category": "pantry"
      },
      {
        "id": "lc-6",
        "quantity": 4,
        "unit": "tbsp",
        "category": "pantry"
      },
      {
        "id": "lc-7",
        "quantity": 300,
        "unit": "g",
        "category": "produce"
      },
      {
        "id": "lc-8",
        "quantity": 400,
        "unit": "g",
        "category": "produce"
      },
      {
        "id": "lc-9",
        "quantity": 30,
        "unit": "g",
        "category": "dairy"
      }
    ]
  },
  {
    "id": "chicken-pot-pie",
    "imageUrl": "/images/recipes/chicken-pot-pie.png",
    "defaultServings": 6,
    "ingredients": [
      {
        "id": "cpp-1",
        "quantity": 500,
        "unit": "g",
        "category": "meat"
      },
      {
        "id": "cpp-2",
        "quantity": 1,
        "unit": "piece",
        "category": "pantry"
      },
      {
        "id": "cpp-3",
        "quantity": 2,
        "unit": "piece",
        "category": "produce"
      },
      {
        "id": "cpp-4",
        "quantity": 150,
        "unit": "g",
        "category": "produce"
      },
      {
        "id": "cpp-5",
        "quantity": 2,
        "unit": "piece",
        "category": "produce"
      },
      {
        "id": "cpp-6",
        "quantity": 1,
        "unit": "piece",
        "category": "produce"
      },
      {
        "id": "cpp-7",
        "quantity": 50,
        "unit": "g",
        "category": "dairy"
      },
      {
        "id": "cpp-8",
        "quantity": 50,
        "unit": "g",
        "category": "pantry"
      },
      {
        "id": "cpp-9",
        "quantity": 400,
        "unit": "ml",
        "category": "pantry"
      },
      {
        "id": "cpp-10",
        "quantity": 100,
        "unit": "ml",
        "category": "dairy"
      },
      {
        "id": "cpp-11",
        "quantity": 1,
        "unit": "tsp",
        "category": "spices"
      }
    ]
  },
  {
    "id": "beef-tacos",
    "imageUrl": "/images/recipes/beef-tacos.png",
    "defaultServings": 4,
    "ingredients": [
      {
        "id": "bt-1",
        "quantity": 500,
        "unit": "g",
        "category": "meat"
      },
      {
        "id": "bt-2",
        "quantity": 12,
        "unit": "piece",
        "category": "pantry"
      },
      {
        "id": "bt-3",
        "quantity": 1,
        "unit": "tsp",
        "category": "spices"
      },
      {
        "id": "bt-4",
        "quantity": 1,
        "unit": "tbsp",
        "category": "spices"
      },
      {
        "id": "bt-5",
        "quantity": 150,
        "unit": "g",
        "category": "produce"
      },
      {
        "id": "bt-6",
        "quantity": 2,
        "unit": "piece",
        "category": "produce"
      },
      {
        "id": "bt-7",
        "quantity": 150,
        "unit": "g",
        "category": "dairy"
      },
      {
        "id": "bt-8",
        "quantity": 100,
        "unit": "ml",
        "category": "dairy"
      },
      {
        "id": "bt-9",
        "quantity": 150,
        "unit": "ml",
        "category": "pantry"
      },
      {
        "id": "bt-10",
        "quantity": 1,
        "unit": "piece",
        "category": "produce"
      }
    ]
  },
  {
    "id": "ramen-bowl",
    "imageUrl": "/images/recipes/ramen-bowl.png",
    "defaultServings": 4,
    "ingredients": [
      {
        "id": "rb-1",
        "quantity": 300,
        "unit": "g",
        "category": "meat"
      },
      {
        "id": "rb-2",
        "quantity": 400,
        "unit": "g",
        "category": "pantry"
      },
      {
        "id": "rb-3",
        "quantity": 1000,
        "unit": "ml",
        "category": "pantry"
      },
      {
        "id": "rb-4",
        "quantity": 4,
        "unit": "tbsp",
        "category": "pantry"
      },
      {
        "id": "rb-5",
        "quantity": 2,
        "unit": "tbsp",
        "category": "pantry"
      },
      {
        "id": "rb-6",
        "quantity": 4,
        "unit": "piece",
        "category": "dairy"
      },
      {
        "id": "rb-7",
        "quantity": 4,
        "unit": "piece",
        "category": "produce"
      },
      {
        "id": "rb-8",
        "quantity": 4,
        "unit": "piece",
        "category": "pantry"
      },
      {
        "id": "rb-9",
        "quantity": 100,
        "unit": "g",
        "category": "produce"
      },
      {
        "id": "rb-10",
        "quantity": 4,
        "unit": "piece",
        "category": "produce"
      },
      {
        "id": "rb-11",
        "quantity": 1,
        "unit": "tbsp",
        "category": "produce"
      }
    ]
  },
  {
    "id": "chicken-alfredo",
    "imageUrl": "/images/recipes/chicken-alfredo.png",
    "defaultServings": 4,
    "ingredients": [
      {
        "id": "ca-1",
        "quantity": 500,
        "unit": "g",
        "category": "meat"
      },
      {
        "id": "ca-2",
        "quantity": 400,
        "unit": "g",
        "category": "pantry"
      },
      {
        "id": "ca-3",
        "quantity": 300,
        "unit": "ml",
        "category": "dairy"
      },
      {
        "id": "ca-4",
        "quantity": 100,
        "unit": "g",
        "category": "dairy"
      },
      {
        "id": "ca-5",
        "quantity": 50,
        "unit": "g",
        "category": "dairy"
      },
      {
        "id": "ca-6",
        "quantity": 4,
        "unit": "piece",
        "category": "produce"
      },
      {
        "id": "ca-7",
        "quantity": 1,
        "unit": "tsp",
        "category": "spices"
      },
      {
        "id": "ca-8",
        "quantity": 2,
        "unit": "tbsp",
        "category": "produce"
      },
      {
        "id": "ca-9",
        "quantity": 0.5,
        "unit": "tsp",
        "category": "spices"
      }
    ]
  },
  {
    "id": "bibimbap",
    "imageUrl": "/images/recipes/bibimbap.png",
    "defaultServings": 4,
    "ingredients": [
      {
        "id": "bib-1",
        "quantity": 400,
        "unit": "g",
        "category": "pantry"
      },
      {
        "id": "bib-2",
        "quantity": 300,
        "unit": "g",
        "category": "meat"
      },
      {
        "id": "bib-3",
        "quantity": 150,
        "unit": "g",
        "category": "produce"
      },
      {
        "id": "bib-4",
        "quantity": 150,
        "unit": "g",
        "category": "produce"
      },
      {
        "id": "bib-5",
        "quantity": 1,
        "unit": "piece",
        "category": "produce"
      },
      {
        "id": "bib-6",
        "quantity": 1,
        "unit": "piece",
        "category": "produce"
      },
      {
        "id": "bib-7",
        "quantity": 4,
        "unit": "piece",
        "category": "dairy"
      },
      {
        "id": "bib-8",
        "quantity": 4,
        "unit": "tbsp",
        "category": "pantry"
      },
      {
        "id": "bib-9",
        "quantity": 2,
        "unit": "tbsp",
        "category": "pantry"
      },
      {
        "id": "bib-10",
        "quantity": 2,
        "unit": "tbsp",
        "category": "pantry"
      },
      {
        "id": "bib-11",
        "quantity": 1,
        "unit": "tbsp",
        "category": "spices"
      }
    ]
  },
  {
    "id": "eggplant-parmesan",
    "imageUrl": "/images/recipes/eggplant-parmesan.png",
    "defaultServings": 4,
    "ingredients": [
      {
        "id": "ep-1",
        "quantity": 2,
        "unit": "piece",
        "category": "produce"
      },
      {
        "id": "ep-2",
        "quantity": 200,
        "unit": "g",
        "category": "pantry"
      },
      {
        "id": "ep-3",
        "quantity": 100,
        "unit": "g",
        "category": "dairy"
      },
      {
        "id": "ep-4",
        "quantity": 200,
        "unit": "g",
        "category": "dairy"
      },
      {
        "id": "ep-5",
        "quantity": 500,
        "unit": "ml",
        "category": "pantry"
      },
      {
        "id": "ep-6",
        "quantity": 3,
        "unit": "piece",
        "category": "dairy"
      },
      {
        "id": "ep-7",
        "quantity": 100,
        "unit": "g",
        "category": "pantry"
      },
      {
        "id": "ep-8",
        "quantity": 3,
        "unit": "tbsp",
        "category": "produce"
      },
      {
        "id": "ep-9",
        "quantity": 100,
        "unit": "ml",
        "category": "pantry"
      }
    ]
  },
  {
    "id": "kung-pao-chicken",
    "imageUrl": "/images/recipes/kung-pao-chicken.png",
    "defaultServings": 4,
    "ingredients": [
      {
        "id": "kpc-1",
        "quantity": 500,
        "unit": "g",
        "category": "meat"
      },
      {
        "id": "kpc-2",
        "quantity": 80,
        "unit": "g",
        "category": "pantry"
      },
      {
        "id": "kpc-3",
        "quantity": 8,
        "unit": "piece",
        "category": "spices"
      },
      {
        "id": "kpc-4",
        "quantity": 3,
        "unit": "tbsp",
        "category": "pantry"
      },
      {
        "id": "kpc-5",
        "quantity": 2,
        "unit": "tbsp",
        "category": "pantry"
      },
      {
        "id": "kpc-6",
        "quantity": 1,
        "unit": "tbsp",
        "category": "pantry"
      },
      {
        "id": "kpc-7",
        "quantity": 4,
        "unit": "piece",
        "category": "produce"
      },
      {
        "id": "kpc-8",
        "quantity": 1,
        "unit": "tbsp",
        "category": "produce"
      },
      {
        "id": "kpc-9",
        "quantity": 4,
        "unit": "piece",
        "category": "produce"
      },
      {
        "id": "kpc-10",
        "quantity": 300,
        "unit": "g",
        "category": "pantry"
      },
      {
        "id": "kpc-11",
        "quantity": 1,
        "unit": "tbsp",
        "category": "pantry"
      }
    ]
  },
  {
    "id": "caprese-chicken",
    "imageUrl": "/images/recipes/caprese-chicken.png",
    "defaultServings": 4,
    "ingredients": [
      {
        "id": "cpc-1",
        "quantity": 4,
        "unit": "piece",
        "category": "meat"
      },
      {
        "id": "cpc-2",
        "quantity": 200,
        "unit": "g",
        "category": "dairy"
      },
      {
        "id": "cpc-3",
        "quantity": 2,
        "unit": "piece",
        "category": "produce"
      },
      {
        "id": "cpc-4",
        "quantity": 15,
        "unit": "g",
        "category": "produce"
      },
      {
        "id": "cpc-5",
        "quantity": 3,
        "unit": "tbsp",
        "category": "pantry"
      },
      {
        "id": "cpc-6",
        "quantity": 3,
        "unit": "tbsp",
        "category": "pantry"
      },
      {
        "id": "cpc-7",
        "quantity": 1,
        "unit": "tsp",
        "category": "spices"
      },
      {
        "id": "cpc-8",
        "quantity": 200,
        "unit": "g",
        "category": "produce"
      }
    ]
  },
  {
    "id": "beef-stroganoff",
    "imageUrl": "/images/recipes/beef-stroganoff.png",
    "defaultServings": 4,
    "ingredients": [
      {
        "id": "bs-1",
        "quantity": 500,
        "unit": "g",
        "category": "meat"
      },
      {
        "id": "bs-2",
        "quantity": 300,
        "unit": "g",
        "category": "produce"
      },
      {
        "id": "bs-3",
        "quantity": 400,
        "unit": "g",
        "category": "pantry"
      },
      {
        "id": "bs-4",
        "quantity": 200,
        "unit": "ml",
        "category": "dairy"
      },
      {
        "id": "bs-5",
        "quantity": 200,
        "unit": "ml",
        "category": "pantry"
      },
      {
        "id": "bs-6",
        "quantity": 1,
        "unit": "piece",
        "category": "produce"
      },
      {
        "id": "bs-7",
        "quantity": 3,
        "unit": "piece",
        "category": "produce"
      },
      {
        "id": "bs-8",
        "quantity": 1,
        "unit": "tbsp",
        "category": "pantry"
      },
      {
        "id": "bs-9",
        "quantity": 40,
        "unit": "g",
        "category": "dairy"
      },
      {
        "id": "bs-10",
        "quantity": 2,
        "unit": "tbsp",
        "category": "produce"
      }
    ]
  },
  {
    "id": "cheesy-pork-quesadillas",
    "imageUrl": "/images/recipes/cheesy-pork-quesadillas.png",
    "defaultServings": 4,
    "ingredients": [
      {
        "id": "cpq-1",
        "quantity": 400,
        "unit": "g",
        "category": "meat"
      },
      {
        "id": "cpq-2",
        "quantity": 8,
        "unit": "piece",
        "category": "pantry"
      },
      {
        "id": "cpq-3",
        "quantity": 200,
        "unit": "g",
        "category": "dairy"
      },
      {
        "id": "cpq-4",
        "quantity": 100,
        "unit": "g",
        "category": "dairy"
      },
      {
        "id": "cpq-5",
        "quantity": 1,
        "unit": "piece",
        "category": "produce"
      },
      {
        "id": "cpq-6",
        "quantity": 1,
        "unit": "piece",
        "category": "produce"
      },
      {
        "id": "cpq-7",
        "quantity": 1,
        "unit": "tsp",
        "category": "spices"
      },
      {
        "id": "cpq-8",
        "quantity": 1,
        "unit": "tsp",
        "category": "spices"
      },
      {
        "id": "cpq-9",
        "quantity": 100,
        "unit": "ml",
        "category": "dairy"
      },
      {
        "id": "cpq-10",
        "quantity": 100,
        "unit": "ml",
        "category": "pantry"
      },
      {
        "id": "cpq-11",
        "quantity": 2,
        "unit": "tbsp",
        "category": "produce"
      },
      {
        "id": "cpq-12",
        "quantity": 2,
        "unit": "tbsp",
        "category": "pantry"
      }
    ]
  },
  {
    "id": "greek-beef-gnocchi",
    "imageUrl": "/images/recipes/greek-beef-gnocchi.png",
    "defaultServings": 4,
    "ingredients": [
      {
        "id": "gbg-1",
        "quantity": 500,
        "unit": "g",
        "category": "pantry"
      },
      {
        "id": "gbg-2",
        "quantity": 400,
        "unit": "g",
        "category": "meat"
      },
      {
        "id": "gbg-3",
        "quantity": 150,
        "unit": "g",
        "category": "dairy"
      },
      {
        "id": "gbg-4",
        "quantity": 250,
        "unit": "g",
        "category": "produce"
      },
      {
        "id": "gbg-5",
        "quantity": 150,
        "unit": "g",
        "category": "produce"
      },
      {
        "id": "gbg-6",
        "quantity": 50,
        "unit": "g",
        "category": "pantry"
      },
      {
        "id": "gbg-7",
        "quantity": 4,
        "unit": "piece",
        "category": "produce"
      },
      {
        "id": "gbg-8",
        "quantity": 1,
        "unit": "tsp",
        "category": "spices"
      },
      {
        "id": "gbg-9",
        "quantity": 3,
        "unit": "tbsp",
        "category": "pantry"
      },
      {
        "id": "gbg-10",
        "quantity": 1,
        "unit": "piece",
        "category": "produce"
      },
      {
        "id": "gbg-11",
        "quantity": 0.5,
        "unit": "piece",
        "category": "produce"
      }
    ]
  },
  {
    "id": "butternut-squash-orzotto",
    "imageUrl": "/images/recipes/butternut-squash-orzotto.png",
    "defaultServings": 4,
    "ingredients": [
      {
        "id": "bso-1",
        "quantity": 300,
        "unit": "g",
        "category": "pantry"
      },
      {
        "id": "bso-2",
        "quantity": 400,
        "unit": "g",
        "category": "produce"
      },
      {
        "id": "bso-3",
        "quantity": 800,
        "unit": "ml",
        "category": "pantry"
      },
      {
        "id": "bso-4",
        "quantity": 12,
        "unit": "piece",
        "category": "produce"
      },
      {
        "id": "bso-5",
        "quantity": 80,
        "unit": "g",
        "category": "dairy"
      },
      {
        "id": "bso-6",
        "quantity": 60,
        "unit": "g",
        "category": "dairy"
      },
      {
        "id": "bso-7",
        "quantity": 1,
        "unit": "piece",
        "category": "produce"
      },
      {
        "id": "bso-8",
        "quantity": 3,
        "unit": "piece",
        "category": "produce"
      },
      {
        "id": "bso-9",
        "quantity": 100,
        "unit": "ml",
        "category": "pantry"
      },
      {
        "id": "bso-10",
        "quantity": 2,
        "unit": "tbsp",
        "category": "pantry"
      },
      {
        "id": "bso-11",
        "quantity": 0.25,
        "unit": "tsp",
        "category": "spices"
      }
    ]
  },
  {
    "id": "bacon-mac-and-cheese",
    "imageUrl": "/images/recipes/bacon-mac-and-cheese.png",
    "defaultServings": 4,
    "ingredients": [
      {
        "id": "bmc-1",
        "quantity": 400,
        "unit": "g",
        "category": "pantry"
      },
      {
        "id": "bmc-2",
        "quantity": 200,
        "unit": "g",
        "category": "meat"
      },
      {
        "id": "bmc-3",
        "quantity": 200,
        "unit": "g",
        "category": "dairy"
      },
      {
        "id": "bmc-4",
        "quantity": 100,
        "unit": "g",
        "category": "dairy"
      },
      {
        "id": "bmc-5",
        "quantity": 50,
        "unit": "g",
        "category": "dairy"
      },
      {
        "id": "bmc-6",
        "quantity": 500,
        "unit": "ml",
        "category": "dairy"
      },
      {
        "id": "bmc-7",
        "quantity": 45,
        "unit": "g",
        "category": "dairy"
      },
      {
        "id": "bmc-8",
        "quantity": 45,
        "unit": "g",
        "category": "pantry"
      },
      {
        "id": "bmc-9",
        "quantity": 1,
        "unit": "tsp",
        "category": "pantry"
      },
      {
        "id": "bmc-10",
        "quantity": 0.5,
        "unit": "tsp",
        "category": "spices"
      },
      {
        "id": "bmc-11",
        "quantity": 0.5,
        "unit": "tsp",
        "category": "spices"
      },
      {
        "id": "bmc-12",
        "quantity": 2,
        "unit": "tbsp",
        "category": "produce"
      }
    ]
  },
  {
    "id": "teppanyaki-beef-udon",
    "imageUrl": "/images/recipes/teppanyaki-beef-udon.png",
    "defaultServings": 4,
    "ingredients": [
      {
        "id": "tbu-1",
        "quantity": 400,
        "unit": "g",
        "category": "pantry"
      },
      {
        "id": "tbu-2",
        "quantity": 500,
        "unit": "g",
        "category": "meat"
      },
      {
        "id": "tbu-3",
        "quantity": 200,
        "unit": "g",
        "category": "produce"
      },
      {
        "id": "tbu-4",
        "quantity": 150,
        "unit": "g",
        "category": "produce"
      },
      {
        "id": "tbu-5",
        "quantity": 1,
        "unit": "piece",
        "category": "produce"
      },
      {
        "id": "tbu-6",
        "quantity": 60,
        "unit": "g",
        "category": "produce"
      },
      {
        "id": "tbu-7",
        "quantity": 4,
        "unit": "piece",
        "category": "produce"
      },
      {
        "id": "tbu-8",
        "quantity": 2,
        "unit": "tbsp",
        "category": "pantry"
      },
      {
        "id": "tbu-9",
        "quantity": 3,
        "unit": "tbsp",
        "category": "pantry"
      },
      {
        "id": "tbu-10",
        "quantity": 4,
        "unit": "tbsp",
        "category": "pantry"
      },
      {
        "id": "tbu-11",
        "quantity": 4,
        "unit": "piece",
        "category": "produce"
      },
      {
        "id": "tbu-12",
        "quantity": 1,
        "unit": "tbsp",
        "category": "produce"
      },
      {
        "id": "tbu-13",
        "quantity": 30,
        "unit": "g",
        "category": "dairy"
      },
      {
        "id": "tbu-14",
        "quantity": 2,
        "unit": "tbsp",
        "category": "pantry"
      },
      {
        "id": "tbu-15",
        "quantity": 1,
        "unit": "tbsp",
        "category": "spices"
      }
    ]
  },
  {
    "id": "crispy-beef-taquitos",
    "imageUrl": "/images/recipes/crispy-beef-taquitos.png",
    "defaultServings": 4,
    "ingredients": [
      {
        "id": "cbt-1",
        "quantity": 400,
        "unit": "g",
        "category": "meat"
      },
      {
        "id": "cbt-2",
        "quantity": 12,
        "unit": "piece",
        "category": "pantry"
      },
      {
        "id": "cbt-3",
        "quantity": 150,
        "unit": "g",
        "category": "dairy"
      },
      {
        "id": "cbt-4",
        "quantity": 100,
        "unit": "g",
        "category": "dairy"
      },
      {
        "id": "cbt-5",
        "quantity": 1,
        "unit": "piece",
        "category": "produce"
      },
      {
        "id": "cbt-6",
        "quantity": 3,
        "unit": "piece",
        "category": "produce"
      },
      {
        "id": "cbt-7",
        "quantity": 1,
        "unit": "tsp",
        "category": "spices"
      },
      {
        "id": "cbt-8",
        "quantity": 1,
        "unit": "tsp",
        "category": "spices"
      },
      {
        "id": "cbt-9",
        "quantity": 100,
        "unit": "ml",
        "category": "pantry"
      },
      {
        "id": "cbt-10",
        "quantity": 100,
        "unit": "ml",
        "category": "dairy"
      },
      {
        "id": "cbt-11",
        "quantity": 2,
        "unit": "tbsp",
        "category": "pantry"
      },
      {
        "id": "cbt-12",
        "quantity": 2,
        "unit": "tbsp",
        "category": "produce"
      }
    ]
  },
  {
    "id": "french-onion-beef-noodles",
    "imageUrl": "/images/recipes/french-onion-beef-noodles.png",
    "defaultServings": 4,
    "ingredients": [
      {
        "id": "fobn-1",
        "quantity": 400,
        "unit": "g",
        "category": "pantry"
      },
      {
        "id": "fobn-2",
        "quantity": 500,
        "unit": "g",
        "category": "meat"
      },
      {
        "id": "fobn-3",
        "quantity": 3,
        "unit": "piece",
        "category": "produce"
      },
      {
        "id": "fobn-4",
        "quantity": 250,
        "unit": "g",
        "category": "produce"
      },
      {
        "id": "fobn-5",
        "quantity": 150,
        "unit": "ml",
        "category": "pantry"
      },
      {
        "id": "fobn-6",
        "quantity": 300,
        "unit": "ml",
        "category": "pantry"
      },
      {
        "id": "fobn-7",
        "quantity": 100,
        "unit": "g",
        "category": "dairy"
      },
      {
        "id": "fobn-8",
        "quantity": 60,
        "unit": "g",
        "category": "dairy"
      },
      {
        "id": "fobn-9",
        "quantity": 4,
        "unit": "piece",
        "category": "produce"
      },
      {
        "id": "fobn-10",
        "quantity": 1,
        "unit": "tsp",
        "category": "spices"
      },
      {
        "id": "fobn-11",
        "quantity": 100,
        "unit": "ml",
        "category": "dairy"
      },
      {
        "id": "fobn-12",
        "quantity": 2,
        "unit": "tbsp",
        "category": "produce"
      }
    ]
  },
  {
    "id": "asian-sesame-chicken-salad",
    "imageUrl": "/images/recipes/asian-sesame-chicken-salad.png",
    "defaultServings": 4,
    "ingredients": [
      {
        "id": "ascs-1",
        "quantity": 500,
        "unit": "g",
        "category": "meat"
      },
      {
        "id": "ascs-2",
        "quantity": 200,
        "unit": "g",
        "category": "produce"
      },
      {
        "id": "ascs-3",
        "quantity": 150,
        "unit": "g",
        "category": "produce"
      },
      {
        "id": "ascs-4",
        "quantity": 2,
        "unit": "piece",
        "category": "produce"
      },
      {
        "id": "ascs-5",
        "quantity": 100,
        "unit": "g",
        "category": "produce"
      },
      {
        "id": "ascs-6",
        "quantity": 200,
        "unit": "g",
        "category": "produce"
      },
      {
        "id": "ascs-7",
        "quantity": 3,
        "unit": "tbsp",
        "category": "pantry"
      },
      {
        "id": "ascs-8",
        "quantity": 3,
        "unit": "tbsp",
        "category": "pantry"
      },
      {
        "id": "ascs-9",
        "quantity": 2,
        "unit": "tbsp",
        "category": "pantry"
      },
      {
        "id": "ascs-10",
        "quantity": 2,
        "unit": "tbsp",
        "category": "pantry"
      },
      {
        "id": "ascs-11",
        "quantity": 1,
        "unit": "tbsp",
        "category": "produce"
      },
      {
        "id": "ascs-12",
        "quantity": 2,
        "unit": "tbsp",
        "category": "spices"
      },
      {
        "id": "ascs-13",
        "quantity": 50,
        "unit": "g",
        "category": "pantry"
      }
    ]
  },
  {
    "id": "spinach-strawberry-salad",
    "imageUrl": "/images/recipes/spinach-strawberry-salad.png",
    "defaultServings": 4,
    "ingredients": [
      {
        "id": "sss-1",
        "quantity": 300,
        "unit": "g",
        "category": "produce"
      },
      {
        "id": "sss-2",
        "quantity": 300,
        "unit": "g",
        "category": "produce"
      },
      {
        "id": "sss-3",
        "quantity": 100,
        "unit": "g",
        "category": "dairy"
      },
      {
        "id": "sss-4",
        "quantity": 80,
        "unit": "g",
        "category": "pantry"
      },
      {
        "id": "sss-5",
        "quantity": 0.5,
        "unit": "piece",
        "category": "produce"
      },
      {
        "id": "sss-6",
        "quantity": 4,
        "unit": "tbsp",
        "category": "pantry"
      },
      {
        "id": "sss-7",
        "quantity": 2,
        "unit": "tbsp",
        "category": "pantry"
      },
      {
        "id": "sss-8",
        "quantity": 1,
        "unit": "tbsp",
        "category": "pantry"
      },
      {
        "id": "sss-9",
        "quantity": 1,
        "unit": "tsp",
        "category": "spices"
      },
      {
        "id": "sss-10",
        "quantity": 1,
        "unit": "tsp",
        "category": "pantry"
      }
    ]
  },
  {
    "id": "classic-cobb-salad",
    "imageUrl": "/images/recipes/classic-cobb-salad.png",
    "defaultServings": 4,
    "ingredients": [
      {
        "id": "ccs-1",
        "quantity": 400,
        "unit": "g",
        "category": "meat"
      },
      {
        "id": "ccs-2",
        "quantity": 2,
        "unit": "piece",
        "category": "produce"
      },
      {
        "id": "ccs-3",
        "quantity": 200,
        "unit": "g",
        "category": "meat"
      },
      {
        "id": "ccs-4",
        "quantity": 4,
        "unit": "piece",
        "category": "dairy"
      },
      {
        "id": "ccs-5",
        "quantity": 2,
        "unit": "piece",
        "category": "produce"
      },
      {
        "id": "ccs-6",
        "quantity": 200,
        "unit": "g",
        "category": "produce"
      },
      {
        "id": "ccs-7",
        "quantity": 100,
        "unit": "g",
        "category": "dairy"
      },
      {
        "id": "ccs-8",
        "quantity": 3,
        "unit": "tbsp",
        "category": "pantry"
      },
      {
        "id": "ccs-9",
        "quantity": 6,
        "unit": "tbsp",
        "category": "pantry"
      },
      {
        "id": "ccs-10",
        "quantity": 1,
        "unit": "tsp",
        "category": "pantry"
      },
      {
        "id": "ccs-11",
        "quantity": 1,
        "unit": "piece",
        "category": "produce"
      },
      {
        "id": "ccs-12",
        "quantity": 2,
        "unit": "tbsp",
        "category": "produce"
      }
    ]
  },
  {
    "id": "carbonara-pasta",
    "imageUrl": "/images/recipes/carbonara-pasta.png",
    "defaultServings": 2,
    "ingredients": [
      {
        "id": "cp-1",
        "quantity": 200,
        "unit": "g",
        "category": "pantry"
      },
      {
        "id": "cp-2",
        "quantity": 150,
        "unit": "g",
        "category": "meat"
      },
      {
        "id": "cp-3",
        "quantity": 3,
        "unit": "piece",
        "category": "dairy"
      },
      {
        "id": "cp-4",
        "quantity": 60,
        "unit": "g",
        "category": "dairy"
      },
      {
        "id": "cp-5",
        "quantity": 2,
        "unit": "piece",
        "category": "produce"
      },
      {
        "id": "cp-6",
        "quantity": 1,
        "unit": "piece",
        "category": "produce"
      },
      {
        "id": "cp-7",
        "quantity": 1,
        "unit": "tsp",
        "category": "spices"
      },
      {
        "id": "cp-8",
        "quantity": 1,
        "unit": "tsp",
        "category": "spices"
      }
    ]
  },
  {
    "id": "garlic-butter-beef-fried-rice",
    "imageUrl": "/images/recipes/garlic-butter-beef-fried-rice.png",
    "defaultServings": 4,
    "ingredients": [
      {
        "id": "gbfr-1",
        "quantity": 400,
        "unit": "g",
        "category": "pantry"
      },
      {
        "id": "gbfr-2",
        "quantity": 350,
        "unit": "g",
        "category": "meat"
      },
      {
        "id": "gbfr-3",
        "quantity": 3,
        "unit": "tbsp",
        "category": "dairy"
      },
      {
        "id": "gbfr-4",
        "quantity": 6,
        "unit": "piece",
        "category": "produce"
      },
      {
        "id": "gbfr-5",
        "quantity": 3,
        "unit": "piece",
        "category": "dairy"
      },
      {
        "id": "gbfr-6",
        "quantity": 3,
        "unit": "tbsp",
        "category": "pantry"
      },
      {
        "id": "gbfr-7",
        "quantity": 2,
        "unit": "tbsp",
        "category": "pantry"
      },
      {
        "id": "gbfr-8",
        "quantity": 1,
        "unit": "tbsp",
        "category": "pantry"
      },
      {
        "id": "gbfr-9",
        "quantity": 4,
        "unit": "piece",
        "category": "produce"
      },
      {
        "id": "gbfr-10",
        "quantity": 1,
        "unit": "piece",
        "category": "produce"
      },
      {
        "id": "gbfr-11",
        "quantity": 100,
        "unit": "g",
        "category": "produce"
      },
      {
        "id": "gbfr-12",
        "quantity": 0.5,
        "unit": "tsp",
        "category": "spices"
      }
    ]
  },
  {
    "id": "galette-bretonne",
    "imageUrl": "/images/recipes/galette-bretonne.png",
    "defaultServings": 4,
    "ingredients": [
      {
        "id": "galette-bretonne-1",
        "quantity": 250,
        "unit": "g",
        "category": "pantry"
      },
      {
        "id": "galette-bretonne-2",
        "quantity": 500,
        "unit": "ml",
        "category": "pantry"
      },
      {
        "id": "galette-bretonne-3",
        "quantity": 5,
        "unit": "piece",
        "category": "produce"
      },
      {
        "id": "galette-bretonne-4",
        "quantity": 1,
        "unit": "tsp",
        "category": "spices"
      },
      {
        "id": "galette-bretonne-5",
        "quantity": 50,
        "unit": "g",
        "category": "dairy"
      },
      {
        "id": "galette-bretonne-6",
        "quantity": 200,
        "unit": "g",
        "category": "meat"
      },
      {
        "id": "galette-bretonne-7",
        "quantity": 150,
        "unit": "g",
        "category": "dairy"
      }
    ]
  },
  {
    "id": "crepe-bretonne",
    "imageUrl": "/images/recipes/crepe-bretonne.png",
    "defaultServings": 4,
    "ingredients": [
      {
        "id": "crepe-bretonne-1",
        "quantity": 250,
        "unit": "g",
        "category": "pantry"
      },
      {
        "id": "crepe-bretonne-2",
        "quantity": 500,
        "unit": "ml",
        "category": "dairy"
      },
      {
        "id": "crepe-bretonne-3",
        "quantity": 3,
        "unit": "piece",
        "category": "produce"
      },
      {
        "id": "crepe-bretonne-4",
        "quantity": 2,
        "unit": "tbsp",
        "category": "pantry"
      },
      {
        "id": "crepe-bretonne-5",
        "quantity": 60,
        "unit": "g",
        "category": "dairy"
      },
      {
        "id": "crepe-bretonne-6",
        "quantity": 1,
        "unit": "tsp",
        "category": "spices"
      },
      {
        "id": "crepe-bretonne-7",
        "quantity": 1,
        "unit": "pinch",
        "category": "spices"
      }
    ]
  }
]
